LICENSE
MANIFEST.in
README.md
pyproject.toml
setup.cfg
src/pytest_pymysql_autorecord/__init__.py
src/pytest_pymysql_autorecord/connect.py
src/pytest_pymysql_autorecord/plugin.py
src/pytest_pymysql_autorecord/py.typed
src/pytest_pymysql_autorecord/util.py
src/pytest_pymysql_autorecord.egg-info/PKG-INFO
src/pytest_pymysql_autorecord.egg-info/SOURCES.txt
src/pytest_pymysql_autorecord.egg-info/dependency_links.txt
src/pytest_pymysql_autorecord.egg-info/entry_points.txt
src/pytest_pymysql_autorecord.egg-info/requires.txt
src/pytest_pymysql_autorecord.egg-info/top_level.txt
src/pytest_pymysql_autorecord/__pycache__/__init__.cpython-310.pyc
src/pytest_pymysql_autorecord/__pycache__/__init__.cpython-37.pyc
src/pytest_pymysql_autorecord/__pycache__/__init__.cpython-39.pyc
src/pytest_pymysql_autorecord/__pycache__/connect.cpython-37.pyc
src/pytest_pymysql_autorecord/__pycache__/connect.cpython-39.pyc
src/pytest_pymysql_autorecord/__pycache__/plugin.cpython-37.pyc
src/pytest_pymysql_autorecord/__pycache__/plugin.cpython-39.pyc
src/pytest_pymysql_autorecord/__pycache__/util.cpython-310.pyc
src/pytest_pymysql_autorecord/__pycache__/util.cpython-37.pyc
src/pytest_pymysql_autorecord/__pycache__/util.cpython-39.pyc