Metadata-Version: 2.1
Name: pytest-pymysql-autorecord
Version: 0.1.0
Summary: Record PyMySQL queries and mock with the stored data.
Home-page: https://github.com/saltastroops/pytest-pymysql-autorecord
Author: Southern African Large Telescope (SALT)
Author-email: salthelp@salt.ac.za
License: MIT
Classifier: License :: OSI Approved :: MIT License
License-File: LICENSE
